{
  "P17": "[X] is located in the country of __",
  "P19": "the city that [X] was born in is __",
  "P20": "the city that [X] died in is __",
  "P26": "[X] is married to __",
  "P30": "the continent that [X] is located in is __",
  "P36": "The capital of [X] is __",
  "P40": "[X]'s child is __",
  "P50": "The author of [X] is __",
  "P69": "The univeristy where [X] was educated is __",
  "P106": "the field that [X] works in is __",
  "P112": "the person who founded [X] is __",
  "P127": "[X] is owned by __",
  "P131": "[X] is located in __",
  "P136": "The type of music that [X] plays is __",
  "P159": "the city that the headquarters of [X] is located in is __",
  "P170": "[X] was created by __",
  "P175": "[X] was performed by __",
  "P176": "The company that produced [X] is __",
  "P264": "[X] is represented by __",
  "P276": "[X] is located in __",
  "P407": "[X] was written in the language of __",
  "P413": "[X] plays the position of __",
  "P495": "the country that [X] was created in is __",
  "P740": "the city where [X] was founded is __",
  "P800": "[X] is famous for __",
  "P364": "The original language of [X] is __",
  "P1412": "the language that [X] speaks of is __",
  "P27": "the country of citizenship of [X] is __",
  "P937": "the city that [X] worked in is __",
  "P37": "The official language of [X] is __",
  "P140": "the religion that [X] is affiliated with is __",
  "P178": "[X] was developed by __",
  "P108": "[X] is employed by __",
  "P641": "the sport that [X] is associated with is __",
  "P190": "The twinned administrative body of [X] is __",
  "P463": "[X] is a member of __",
  "P449": "The origianl broadcaster of [X] is __",
  "P35": "The name of the current head of state of [X] is __",
  "P286": "The head coach of [X] is __",
  "P1308": "The [X] is __",
  "P488": "The chairperson of [X] is __",
  "P169": "The chief executive officer of [X] is __",
  "P1037": "The director of [X] is __",
  "P6": "The name of the current head of the [X] government is __"
}